{
  "dates": [
    {
      "id": "date-quiet-walk",
      "name": "Quiet Walk in the Gardens",
      "description": "A peaceful stroll through the house gardens, enjoying each other's company in silence or soft conversation.",
      "cost": 0,
      "durationHours": 1,
      "preferredTimeSlot": "evening",
      "requiredIntimacyStage": "affinity",
      "traitPreferences": {
        "empathy": 1.2,
        "curiosity": 1.1
      },
      "skillPreferences": {
        "performance": 0.8
      },
      "relationshipRewards": {
        "affinity": { "min": 3, "max": 6 },
        "trust": { "min": 2, "max": 4 },
        "respect": { "min": 1, "max": 3 }
      },
      "outcomes": [
        {
          "id": "walk-silent-comfort",
          "text": "You walk together in comfortable silence. The evening air is cool, and for a moment, the world feels still.",
          "axesDeltas": { "trust": 2, "affinity": 3 }
        },
        {
          "id": "walk-deep-talk",
          "text": "The quiet walk opens a door to conversation neither of you expected. Secrets and dreams spill into the twilight.",
          "axesDeltas": { "trust": 4, "affinity": 5, "respect": 2 }
        },
        {
          "id": "walk-awkward-silence",
          "text": "The silence stretches too long. You both feel the weight of things unsaid, but there's no harm done.",
          "axesDeltas": { "affinity": 1 }
        }
      ]
    },
    {
      "id": "date-shared-meal",
      "name": "Shared Meal",
      "description": "A simple meal together, prepared with care. Food has always been a language of its own.",
      "cost": 15,
      "durationHours": 2,
      "preferredTimeSlot": "evening",
      "requiredIntimacyStage": "affinity",
      "traitPreferences": {
        "empathy": 1.3,
        "prudence": 1.1
      },
      "skillPreferences": {
        "administration": 0.9
      },
      "relationshipRewards": {
        "affinity": { "min": 4, "max": 8 },
        "trust": { "min": 3, "max": 5 },
        "loyalty": { "min": 1, "max": 3 }
      },
      "outcomes": [
        {
          "id": "meal-warmth",
          "text": "The meal is simple but warm. You share bread and stories, and for a while, the house feels like a home.",
          "axesDeltas": { "affinity": 5, "trust": 3, "loyalty": 2 }
        },
        {
          "id": "meal-celebration",
          "text": "Something about tonight makes the food taste better. Laughter comes easily, and you both linger at the table long after.",
          "axesDeltas": { "affinity": 7, "trust": 4, "loyalty": 3 }
        },
        {
          "id": "meal-meh",
          "text": "The meal is adequate. Nothing special, but nothing wrong either. A quiet evening shared.",
          "axesDeltas": { "affinity": 2, "trust": 1 }
        }
      ]
    },
    {
      "id": "date-music-night",
      "name": "Music and Stories",
      "description": "One of you plays while the other listens. Music carries memories and emotions words cannot reach.",
      "cost": 5,
      "durationHours": 2,
      "preferredTimeSlot": "night",
      "requiredIntimacyStage": "attachment",
      "traitPreferences": {
        "empathy": 1.4,
        "vanity": 0.9
      },
      "skillPreferences": {
        "performance": 1.5,
        "academics": 1.2
      },
      "relationshipRewards": {
        "affinity": { "min": 5, "max": 10 },
        "trust": { "min": 4, "max": 7 },
        "respect": { "min": 2, "max": 5 }
      },
      "outcomes": [
        {
          "id": "music-vulnerability",
          "text": "The music opens something deep. You see a side of them you've never known, and they see yours in return.",
          "axesDeltas": { "affinity": 8, "trust": 6, "respect": 3 }
        },
        {
          "id": "music-harmony",
          "text": "Your voices blend together in ways that surprise you both. For a moment, you feel perfectly in sync.",
          "axesDeltas": { "affinity": 6, "trust": 4, "respect": 2 }
        },
        {
          "id": "music-off-key",
          "text": "The tune falters, and you both laugh. It's imperfect, but the laughter is genuine.",
          "axesDeltas": { "affinity": 3, "trust": 2 }
        }
      ]
    },
    {
      "id": "date-workshop-project",
      "name": "Workshop Project",
      "description": "Working together on a small repair or creation. There's intimacy in shared labor and tangible results.",
      "cost": 10,
      "durationHours": 3,
      "preferredTimeSlot": "afternoon",
      "requiredIntimacyStage": "affinity",
      "traitPreferences": {
        "prudence": 1.2,
        "ambition": 1.1
      },
      "skillPreferences": {
        "engineering": 1.3,
        "crafting": 1.3,
        "administration": 1.0
      },
      "relationshipRewards": {
        "affinity": { "min": 3, "max": 6 },
        "respect": { "min": 4, "max": 8 },
        "loyalty": { "min": 2, "max": 4 }
      },
      "outcomes": [
        {
          "id": "workshop-success",
          "text": "The project comes together better than expected. You look at what you've built and feel a quiet pride in the work—and in each other.",
          "axesDeltas": { "affinity": 5, "respect": 6, "loyalty": 3 }
        },
        {
          "id": "workshop-struggle",
          "text": "It's harder than anticipated, but you persist. The shared struggle forges something stronger than ease ever could.",
          "axesDeltas": { "respect": 5, "loyalty": 4, "affinity": 2 }
        },
        {
          "id": "workshop-messy",
          "text": "The project is a mess, but you're both laughing by the end. Sometimes failure is more memorable than success.",
          "axesDeltas": { "affinity": 3, "respect": 1 }
        }
      ]
    },
    {
      "id": "date-private-ritual",
      "name": "Private Ritual",
      "description": "An intimate moment that transcends words. This is for those who have already crossed the threshold together.",
      "cost": 0,
      "durationHours": 2,
      "preferredTimeSlot": "night",
      "requiredIntimacyStage": "committed",
      "traitPreferences": {
        "empathy": 1.5,
        "dominance": 1.0,
        "loyalty": 1.3
      },
      "skillPreferences": {},
      "relationshipRewards": {
        "affinity": { "min": 6, "max": 12 },
        "trust": { "min": 5, "max": 10 },
        "loyalty": { "min": 4, "max": 8 }
      },
      "outcomes": [
        {
          "id": "ritual-union",
          "text": "There are no words for what passes between you. When it ends, you're both changed—bound tighter than before.",
          "axesDeltas": { "affinity": 10, "trust": 8, "loyalty": 6 }
        },
        {
          "id": "ritual-quiet",
          "text": "A quiet intimacy, gentle and sure. You rest together in the aftermath, and the world feels distant and unimportant.",
          "axesDeltas": { "affinity": 7, "trust": 6, "loyalty": 5 }
        },
        {
          "id": "ritual-tender",
          "text": "The moment is tender, almost fragile. You both handle it with care, and it becomes something precious.",
          "axesDeltas": { "affinity": 8, "trust": 7, "loyalty": 4 }
        }
      ]
    },
    {
      "id": "date-district-exploration",
      "name": "District Exploration",
      "description": "Walking the districts together, seeing the city through each other's eyes. A chance to share your world.",
      "cost": 8,
      "durationHours": 3,
      "preferredTimeSlot": "afternoon",
      "requiredIntimacyStage": "attachment",
      "traitPreferences": {
        "curiosity": 1.4,
        "ambition": 1.2
      },
      "skillPreferences": {
        "negotiation": 1.1,
        "survival": 1.0
      },
      "relationshipRewards": {
        "affinity": { "min": 4, "max": 7 },
        "respect": { "min": 3, "max": 6 },
        "trust": { "min": 2, "max": 5 }
      },
      "outcomes": [
        {
          "id": "explore-discovery",
          "text": "You find a corner of the city neither of you knew. It becomes *your* place now—a secret shared.",
          "axesDeltas": { "affinity": 6, "respect": 4, "trust": 3 }
        },
        {
          "id": "explore-tension",
          "text": "The district is tense today, but you navigate it together. The shared vigilance brings you closer.",
          "axesDeltas": { "respect": 5, "trust": 4, "affinity": 2 }
        },
        {
          "id": "explore-pleasant",
          "text": "A pleasant walk through familiar streets. Nothing extraordinary, but the company makes it worthwhile.",
          "axesDeltas": { "affinity": 4, "respect": 2 }
        }
      ]
    },
    {
      "id": "date-quiet-morning",
      "name": "Quiet Morning Together",
      "description": "Waking before the world, sharing coffee or tea in the pale morning light. A rare moment of peace.",
      "cost": 3,
      "durationHours": 1,
      "preferredTimeSlot": "morning",
      "requiredIntimacyStage": "attachment",
      "traitPreferences": {
        "empathy": 1.3,
        "prudence": 1.2
      },
      "skillPreferences": {},
      "relationshipRewards": {
        "affinity": { "min": 4, "max": 7 },
        "trust": { "min": 4, "max": 6 },
        "loyalty": { "min": 2, "max": 4 }
      },
      "outcomes": [
        {
          "id": "morning-peace",
          "text": "The house is silent except for the clink of cups. You watch them in the morning light and feel something settle in your chest.",
          "axesDeltas": { "affinity": 5, "trust": 5, "loyalty": 3 }
        },
        {
          "id": "morning-plans",
          "text": "You talk about things that might happen, futures that might be. For the first time, the future doesn't feel like a threat.",
          "axesDeltas": { "affinity": 6, "trust": 4, "loyalty": 4 }
        },
        {
          "id": "morning-simple",
          "text": "Just coffee and quiet. But it's enough.",
          "axesDeltas": { "affinity": 3, "trust": 3 }
        }
      ]
    }
  ]
}
